MANIFEST.in
README.rst
setup.py
collective/__init__.py
collective.tinymceplugins.advfilelinks.egg-info/PKG-INFO
collective.tinymceplugins.advfilelinks.egg-info/SOURCES.txt
collective.tinymceplugins.advfilelinks.egg-info/dependency_links.txt
collective.tinymceplugins.advfilelinks.egg-info/entry_points.txt
collective.tinymceplugins.advfilelinks.egg-info/namespace_packages.txt
collective.tinymceplugins.advfilelinks.egg-info/not-zip-safe
collective.tinymceplugins.advfilelinks.egg-info/requires.txt
collective.tinymceplugins.advfilelinks.egg-info/top_level.txt
collective/tinymceplugins/__init__.py
collective/tinymceplugins/advfilelinks/__init__.py
collective/tinymceplugins/advfilelinks/adapters.py
collective/tinymceplugins/advfilelinks/configure.zcml
collective/tinymceplugins/advfilelinks/interfaces.py
collective/tinymceplugins/advfilelinks/setuphandlers.py
collective/tinymceplugins/advfilelinks/upgrades.zcml
collective/tinymceplugins/advfilelinks/Extensions/install.py
collective/tinymceplugins/advfilelinks/browser/__init__.py
collective/tinymceplugins/advfilelinks/browser/configure.zcml
collective/tinymceplugins/advfilelinks/browser/interfaces.py
collective/tinymceplugins/advfilelinks/browser/tiny_filetypes.css
collective/tinymceplugins/advfilelinks/browser/view.py
collective/tinymceplugins/advfilelinks/browser/jbot_templates/Products.TinyMCE.skins.tinymce.plugins.plonelink.editor_plugin.js
collective/tinymceplugins/advfilelinks/browser/jbot_templates/Products.TinyMCE.skins.tinymce.plugins.plonelink.js.plonelink.js
collective/tinymceplugins/advfilelinks/browser/jbot_templates/Products.TinyMCE.skins.tinymce.plugins.plonelink.plonelink.htm.pt
collective/tinymceplugins/advfilelinks/browser/resources/csv.png
collective/tinymceplugins/advfilelinks/browser/resources/zip.png
collective/tinymceplugins/advfilelinks/locales/collective.tinymceplugins.advfilelinks-manual.pot
collective/tinymceplugins/advfilelinks/locales/collective.tinymceplugins.advfilelinks.pot
collective/tinymceplugins/advfilelinks/locales/rebuildPo.sh
collective/tinymceplugins/advfilelinks/locales/it/LC_MESSAGES/collective.tinymceplugins.advfilelinks.mo
collective/tinymceplugins/advfilelinks/locales/it/LC_MESSAGES/collective.tinymceplugins.advfilelinks.po
collective/tinymceplugins/advfilelinks/profiles/default/browserlayer.xml
collective/tinymceplugins/advfilelinks/profiles/default/collective.tinymceplugins.advfilelinks.txt
collective/tinymceplugins/advfilelinks/profiles/default/cssregistry.xml
