Metadata-Version: 1.0
Name: collective.tinymceplugins.advfilelinks
Version: 1.3.2
Summary: An advanced Plone TinyMCE plugin for handling links to files
Home-page: http://plone.org/products/collective.tinymceplugins.advfilelinks
Author: RedTurtle Technology
Author-email: sviluppoplone@redturtle.it
License: GPL
Keywords: tinymce plugin file link
Platform: UNKNOWN
Classifier: Development Status :: 5 - Production/Stable
Classifier: Framework :: Plone
Classifier: Framework :: Plone :: 3.3
Classifier: Framework :: Plone :: 4.0
Classifier: Framework :: Plone :: 4.1
Classifier: Framework :: Plone :: 4.2
Classifier: Programming Language :: Python
Classifier: Programming Language :: JavaScript
